sahara_plugin_ambari/__init__.py
sahara_plugin_ambari/i18n.py
sahara_plugin_ambari/locale/de/LC_MESSAGES/sahara_plugin_ambari.po
sahara_plugin_ambari/locale/en_GB/LC_MESSAGES/sahara_plugin_ambari.po
sahara_plugin_ambari/locale/id/LC_MESSAGES/sahara_plugin_ambari.po
sahara_plugin_ambari/plugins/__init__.py
sahara_plugin_ambari/plugins/ambari/__init__.py
sahara_plugin_ambari/plugins/ambari/client.py
sahara_plugin_ambari/plugins/ambari/common.py
sahara_plugin_ambari/plugins/ambari/configs.py
sahara_plugin_ambari/plugins/ambari/deploy.py
sahara_plugin_ambari/plugins/ambari/edp_engine.py
sahara_plugin_ambari/plugins/ambari/ha_helper.py
sahara_plugin_ambari/plugins/ambari/health.py
sahara_plugin_ambari/plugins/ambari/plugin.py
sahara_plugin_ambari/plugins/ambari/requests_helper.py
sahara_plugin_ambari/plugins/ambari/validation.py
sahara_plugin_ambari/plugins/ambari/resources/configs-2.3.json
sahara_plugin_ambari/plugins/ambari/resources/configs-2.4.json
sahara_plugin_ambari/plugins/ambari/resources/configs-2.5.json
sahara_plugin_ambari/plugins/ambari/resources/configs-2.6.json
sahara_plugin_ambari/plugins/ambari/resources/generate_config.py
sahara_plugin_ambari/plugins/ambari/resources/images/image.yaml
sahara_plugin_ambari/plugins/ambari/resources/images/centos/disable_ambari
sahara_plugin_ambari/plugins/ambari/resources/images/centos/disable_certificate_check
sahara_plugin_ambari/plugins/ambari/resources/images/centos/disable_firewall
sahara_plugin_ambari/plugins/ambari/resources/images/centos/disable_selinux
sahara_plugin_ambari/plugins/ambari/resources/images/centos/setup_java_home
sahara_plugin_ambari/plugins/ambari/resources/images/centos/unlimited_security_artifacts
sahara_plugin_ambari/plugins/ambari/resources/images/centos/wget_repo
sahara_plugin_ambari/plugins/ambari/resources/images/common/add_jar
sahara_plugin_ambari/plugins/ambari/resources/images/common/fix_tls_ambari_agent
sahara_plugin_ambari-10.0.0.dist-info/AUTHORS
sahara_plugin_ambari-10.0.0.dist-info/LICENSE
sahara_plugin_ambari-10.0.0.dist-info/METADATA
sahara_plugin_ambari-10.0.0.dist-info/WHEEL
sahara_plugin_ambari-10.0.0.dist-info/entry_points.txt
sahara_plugin_ambari-10.0.0.dist-info/pbr.json
sahara_plugin_ambari-10.0.0.dist-info/top_level.txt
sahara_plugin_ambari-10.0.0.dist-info/RECORD
